LICENSE.txt
MANIFEST.in
README.md
setup.cfg
setup.py
sitecomber_article_tests/__init__.py
sitecomber_article_tests/tests.py
sitecomber_article_tests.egg-info/PKG-INFO
sitecomber_article_tests.egg-info/SOURCES.txt
sitecomber_article_tests.egg-info/dependency_links.txt
sitecomber_article_tests.egg-info/requires.txt
sitecomber_article_tests.egg-info/top_level.txt
sitecomber_article_tests/__pycache__/__init__.cpython-37.pyc
sitecomber_article_tests/__pycache__/dictionary.cpython-37.pyc
sitecomber_article_tests/__pycache__/tests.cpython-37.pyc
sitecomber_article_tests/__pycache__/utils.cpython-37.pyc
sitecomber_article_tests/unit_tests/__init__.py
sitecomber_article_tests/unit_tests/placeholder.py
sitecomber_article_tests/unit_tests/spelling.py
sitecomber_article_tests/unit_tests/__pycache__/__init__.cpython-37.pyc
sitecomber_article_tests/unit_tests/__pycache__/placeholder.cpython-37.pyc
sitecomber_article_tests/unit_tests/__pycache__/spelling.cpython-37.pyc
sitecomber_article_tests/utils/__init__.py
sitecomber_article_tests/utils/article.py
sitecomber_article_tests/utils/dictionary.py
sitecomber_article_tests/utils/spelling.py
sitecomber_article_tests/utils/__pycache__/__init__.cpython-37.pyc
sitecomber_article_tests/utils/__pycache__/article.cpython-37.pyc
sitecomber_article_tests/utils/__pycache__/dictionary.cpython-37.pyc
sitecomber_article_tests/utils/__pycache__/spelling.cpython-37.pyc